mcp_use/__init__.py
mcp_use/cli.py
mcp_use/client.py
mcp_use/config.py
mcp_use/exceptions.py
mcp_use/logging.py
mcp_use/session.py
mcp_use/utils.py
mcp_use/adapters/__init__.py
mcp_use/adapters/base.py
mcp_use/adapters/langchain_adapter.py
mcp_use/agents/__init__.py
mcp_use/agents/base.py
mcp_use/agents/mcpagent.py
mcp_use/agents/remote.py
mcp_use/agents/prompts/system_prompt_builder.py
mcp_use/agents/prompts/templates.py
mcp_use/auth/__init__.py
mcp_use/auth/bearer.py
mcp_use/auth/oauth.py
mcp_use/auth/oauth_callback.py
mcp_use/connectors/__init__.py
mcp_use/connectors/base.py
mcp_use/connectors/http.py
mcp_use/connectors/sandbox.py
mcp_use/connectors/stdio.py
mcp_use/connectors/utils.py
mcp_use/connectors/websocket.py
mcp_use/errors/__init__.py
mcp_use/errors/error_formatting.py
mcp_use/managers/__init__.py
mcp_use/managers/base.py
mcp_use/managers/server_manager.py
mcp_use/managers/tools/__init__.py
mcp_use/managers/tools/base_tool.py
mcp_use/managers/tools/connect_server.py
mcp_use/managers/tools/disconnect_server.py
mcp_use/managers/tools/get_active_server.py
mcp_use/managers/tools/list_servers_tool.py
mcp_use/managers/tools/search_tools.py
mcp_use/observability/__init__.py
mcp_use/observability/callbacks_manager.py
mcp_use/observability/laminar.py
mcp_use/observability/langfuse.py
mcp_use/task_managers/__init__.py
mcp_use/task_managers/base.py
mcp_use/task_managers/sse.py
mcp_use/task_managers/stdio.py
mcp_use/task_managers/streamable_http.py
mcp_use/task_managers/websocket.py
mcp_use/telemetry/__init__.py
mcp_use/telemetry/events.py
mcp_use/telemetry/telemetry.py
mcp_use/telemetry/utils.py
mcp_use/types/http.py
mcp_use/types/sandbox.py
hud_mcp_use_python_sdk-2.3.20.dist-info/METADATA
hud_mcp_use_python_sdk-2.3.20.dist-info/WHEEL
hud_mcp_use_python_sdk-2.3.20.dist-info/entry_points.txt
hud_mcp_use_python_sdk-2.3.20.dist-info/licenses/LICENSE
hud_mcp_use_python_sdk-2.3.20.dist-info/RECORD
