Metadata-Version: 2.4
Name: hud-mcp-use-python-sdk
Version: 2.3.20
Summary: MCP Library for LLMs
Author-email: Pietro Zullo <pietro.zullo@gmail.com>
License: MIT
License-File: LICENSE
Classifier: Development Status :: 3 - Alpha
Classifier: Intended Audience :: Developers
Classifier: License :: OSI Approved :: MIT License
Classifier: Operating System :: OS Independent
Classifier: Programming Language :: Python :: 3
Classifier: Programming Language :: Python :: 3.11
Classifier: Programming Language :: Python :: 3.12
Classifier: Topic :: Software Development :: Libraries :: Python Modules
Requires-Python: >=3.11
Requires-Dist: aiohttp>=3.9.0
Requires-Dist: authlib>=1.6.3
Requires-Dist: hud-mcp-python-sdk>=3.13.2
Requires-Dist: jsonschema-pydantic>=0.1.0
Requires-Dist: langchain>=0.1.0
Requires-Dist: posthog>=4.8.0
Requires-Dist: pydantic>=2.0.0
Requires-Dist: python-dotenv>=1.0.0
Requires-Dist: scarf-sdk>=0.1.0
Requires-Dist: websockets>=15.0
Provides-Extra: anthropic
Requires-Dist: langchain-anthropic; extra == 'anthropic'
Provides-Extra: dev
Requires-Dist: black>=23.9.0; extra == 'dev'
Requires-Dist: fastapi; extra == 'dev'
Requires-Dist: fastmcp==2.10.5; extra == 'dev'
Requires-Dist: isort>=5.12.0; extra == 'dev'
Requires-Dist: mypy>=1.5.0; extra == 'dev'
Requires-Dist: pytest-asyncio>=0.21.0; extra == 'dev'
Requires-Dist: pytest-cov>=4.1.0; extra == 'dev'
Requires-Dist: pytest>=7.4.0; extra == 'dev'
Requires-Dist: ruff>=0.1.0; extra == 'dev'
Provides-Extra: e2b
Requires-Dist: e2b-code-interpreter>=1.5.0; extra == 'e2b'
Provides-Extra: openai
Requires-Dist: langchain-openai; extra == 'openai'
Provides-Extra: search
Requires-Dist: fastembed>=0.0.1; extra == 'search'
